caerp_oidc_client/__init__.py
caerp_oidc_client/exceptions.py
caerp_oidc_client/interfaces.py
caerp_oidc_client/models.py
caerp_oidc_client/services.py
caerp_oidc_client/utils.py
caerp_oidc_client/views.py
caerp_oidc_client-2025.1.2.dist-info/licenses/LICENSE.txt
caerp_oidc_client-2025.1.2.dist-info/METADATA
caerp_oidc_client-2025.1.2.dist-info/WHEEL
caerp_oidc_client-2025.1.2.dist-info/top_level.txt
caerp_oidc_client-2025.1.2.dist-info/RECORD
