Metadata-Version: 2.4
Name: caerp_oidc_client
Version: 2025.1.2
Summary: OpenID Connect client for CAERP
Home-page: https://framagit.org/caerp/caerp_oidc_client
Author: Gaston Tjebbes - Majerti
Author-email: tech@majerti.fr
License: GPLv3
Classifier: Intended Audience :: Developers
Classifier: License :: OSI Approved :: GNU General Public License v3 (GPLv3)
Classifier: Operating System :: OS Independent
Classifier: Programming Language :: Python
Classifier: Programming Language :: Python :: 3
Classifier: Programming Language :: Python :: 3.7
Classifier: Framework :: Pyramid
Requires-Python: >=3.9, <4
License-File: LICENSE.txt
Requires-Dist: pyjwt
Requires-Dist: requests
Dynamic: author
Dynamic: author-email
Dynamic: classifier
Dynamic: description
Dynamic: description-content-type
Dynamic: home-page
Dynamic: license
Dynamic: license-file
Dynamic: requires-dist
Dynamic: requires-python
Dynamic: summary
